MANIFEST.in
README.rst
ez_setup.py
networkxgmml.py
setup.py
example/example-color.py
example/export-to-cytoscape.py
example/import-from-cytoscape.py
example/mirtarbase-example.py
example/mirtarbase-sample.xgmml
example/node-colors.xgmml
example/yeast-ppi.xgmml
networkxgmml.egg-info/PKG-INFO
networkxgmml.egg-info/SOURCES.txt
networkxgmml.egg-info/dependency_links.txt
networkxgmml.egg-info/requires.txt
networkxgmml.egg-info/top_level.txt