Metadata-Version: 1.0
Name: networkxgmml
Version: 0.1.6
Summary: XGMML parser for networkx
Home-page: https://github.com/informationsea/networkxxgmml
Author: Yasunobu OKAMURA
Author-email: okamura@informationsea.info
License: UNKNOWN
Platform: UNKNOWN
